module_sdk/__init__.py
module_sdk/central.py
module_sdk/datasets.py
module_sdk/ethereum.py
module_sdk/metadata.py
module_sdk/modulesdk.py
module_sdk/nft.py
module_sdk/types.py
module_sdk-0.1.1.dist-info/LICENSE
module_sdk-0.1.1.dist-info/METADATA
module_sdk-0.1.1.dist-info/WHEEL
module_sdk-0.1.1.dist-info/top_level.txt
module_sdk-0.1.1.dist-info/RECORD
