Metadata-Version: 2.1
Name: module-sdk
Version: 0.1.1
Summary: A python SDK for The Module API
Home-page: https://github.com/jerempjerem/Module-SDK-Python
Author: jerempjerem
Maintainer: Jerem
License: MIT license
Project-URL: Source, https://github.com/jerempjerem/Module-SDK-Python
Keywords: opensea,nft,non fungible token,crypto,stream
Classifier: Development Status :: 4 - Beta
Classifier: Intended Audience :: Developers
Classifier: Environment :: Web Environment
Classifier: License :: OSI Approved :: MIT License
Classifier: Natural Language :: English
Classifier: Programming Language :: Python
Classifier: Programming Language :: Python :: 3
Classifier: Programming Language :: Python :: 3.6
Classifier: Programming Language :: Python :: 3.7
Classifier: Programming Language :: Python :: 3.8
Classifier: Topic :: Internet
Classifier: Topic :: Internet :: WWW/HTTP :: HTTP Servers
Classifier: Topic :: Office/Business :: Financial
Classifier: Topic :: Software Development :: Libraries
Classifier: Topic :: Software Development :: Libraries :: Python Modules
Classifier: Topic :: Utilities
Requires-Python: >=3.6
License-File: LICENSE
Requires-Dist: pip (>=21.1)
Requires-Dist: termcolor (>=1.1.0)
Requires-Dist: httpx (>=0.20.0)
